.DS_Store
pyvoiceai/__init__.py
pyvoiceai/app_asr.py
pyvoiceai/app_asr_base_api.py
pyvoiceai/app_auth_api.py
pyvoiceai/app_client_api.py
pyvoiceai/app_group_api.py
pyvoiceai/app_voiceprint_api.py
pyvoiceai/baseapi.py
pyvoiceai/log.py
pyvoiceai-1.3.11.dist-info/METADATA
pyvoiceai-1.3.11.dist-info/WHEEL
pyvoiceai-1.3.11.dist-info/top_level.txt
pyvoiceai-1.3.11.dist-info/RECORD
