Metadata-Version: 2.1
Name: pyvoiceai
Version: 1.3.11
Summary: VoiceaiTech Python SDK
Home-page: https://pypi.org/project/pyvoiceai/
Author: voiceai
Author-email: voiceai-github@voiceaitech.com
License: UNKNOWN
Platform: any
Requires-Python: >=2.7, !=3.0.*, !=3.1.*, !=3.2.*, !=3.3.*
Requires-Dist: requests (>=2.19.1)
Requires-Dist: pycryptodomex (>=3.6.6)
Requires-Dist: pyOpenSSL (>=18.0.0)
Requires-Dist: ws4py (>=0.5.1)
Requires-Dist: PyAudio (>=0.2.11)
